djapi/__init__.py
djapi/auth.py
djapi/response.py
djapi/authtoken/__init__.py
djapi/authtoken/admin.py
djapi/authtoken/models.py
djapi/authtoken/migrations/0001_initial.py
djapi/authtoken/migrations/__init__.py
djapi-0.3.dist-info/LICENSE
djapi-0.3.dist-info/METADATA
djapi-0.3.dist-info/WHEEL
djapi-0.3.dist-info/top_level.txt
djapi-0.3.dist-info/RECORD
